{"sections":[{"title":"Morley\/Canon","level":1,"content":[{"type":"paragraph","text":"Morley was a male Anacondan native to Lotho Minor who lived during the Clone Wars."}],"images":[{"src":"http:\/\/img2.wikia.nocookie.net\/__cb20140430172811\/starwars\/images\/3\/3c\/Eras-canon.png"}]},{"title":"Appearances","level":2,"content":[{"type":"list","elements":[{"text":"Star Wars: The Clone Wars \u2013 \"Brothers\"","elements":[]},{"text":"Star Wars: The Clone Wars \u2013 \"Revival\"","elements":[]}]}],"images":[]},{"title":"Sources","level":2,"content":[{"type":"list","elements":[{"text":"\u00a0Brothers Trivia on StarWars.com","elements":[]},{"text":"\u00a0\"Drawing from the Imagination: Mythological Creatures in Star Wars, Part 1,\" The Official Star Wars Blog","elements":[]},{"text":"\u00a0Morley in the Encyclopedia","elements":[]},{"text":"\u00a0Darth Maul in the Encyclopedia","elements":[]},{"text":"\u00a0Morley in the Databank","elements":[]}]}],"images":[]}]}